MANIFEST.in
README.md
setup.py
pyworld2/__init__.py
pyworld2/functions_switch_default.json
pyworld2/functions_switch_scenario_nr.json
pyworld2/functions_table_default.json
pyworld2/test_world2.py
pyworld2/utils.py
pyworld2/world2.py
pyworld2.egg-info/PKG-INFO
pyworld2.egg-info/SOURCES.txt
pyworld2.egg-info/dependency_links.txt
pyworld2.egg-info/requires.txt
pyworld2.egg-info/top_level.txt