Metadata-Version: 1.1
Name: pyworld2
Version: 1.1
Summary: A Python implementation of the model World2.
Home-page: http://github.com/cvanwynsberghe/pyworld2
Author: Charles Vanwynsberghe
Author-email: UNKNOWN
License: MIT
Download-URL: https://github.com/cvanwynsberghe/pyworld2/archive/v1.0.tar.gz
Platform: UNKNOWN
Classifier: Programming Language :: Python
Classifier: Natural Language :: English
Classifier: Operating System :: OS Independent
Classifier: Topic :: Scientific/Engineering
Classifier: Topic :: Education
Classifier: Intended Audience :: Science/Research
Classifier: Intended Audience :: Education
Classifier: License :: OSI Approved :: MIT License
